__init__.py
omop_schema/__init__.py
omop_schema/convert.py
omop_schema/utils.py
omop_schema/validate.py
omop_schema/schema/__init__.py
omop_schema/schema/base.py
omop_schema/schema/v4.py
omop_schema/schema/v5_0.py
omop_schema/schema/v5_3.py
omop_schema/schema/v5_4.py
omop_schema-0.0.3.dist-info/licenses/LICENSE
omop_schema-0.0.3.dist-info/METADATA
omop_schema-0.0.3.dist-info/WHEEL
omop_schema-0.0.3.dist-info/top_level.txt
omop_schema-0.0.3.dist-info/RECORD
