Metadata-Version: 2.4
Name: omop_schema
Version: 0.0.3
Summary: A package to read in and convert OMOP data to the right schema.
Author-email: Robin van de Water <robin.vandewater@hpi.de>
Project-URL: Homepage, https://github.com/rvandewater/omop_schema
Project-URL: Issues, https://github.com/rvandewater/omop_schema/issues
Classifier: Programming Language :: Python :: 3
Classifier: License :: OSI Approved :: MIT License
Classifier: Operating System :: OS Independent
Requires-Python: >=3.10
License-File: LICENSE
Requires-Dist: pyarrow
Provides-Extra: dev
Requires-Dist: pre-commit<4; extra == "dev"
Provides-Extra: tests
Requires-Dist: pytest; extra == "tests"
Requires-Dist: pytest-cov; extra == "tests"
Provides-Extra: polars
Requires-Dist: polars>=0.16.0; extra == "polars"
Provides-Extra: pandas
Requires-Dist: pandas>=1.3.0; extra == "pandas"
Dynamic: license-file
